odoo/addons/sale_blanket_order_invoice_shipping_partner/LICENSE
odoo/addons/sale_blanket_order_invoice_shipping_partner/README.rst
odoo/addons/sale_blanket_order_invoice_shipping_partner/__init__.py
odoo/addons/sale_blanket_order_invoice_shipping_partner/__manifest__.py
odoo/addons/sale_blanket_order_invoice_shipping_partner/i18n/de.po
odoo/addons/sale_blanket_order_invoice_shipping_partner/images/screen.png
odoo/addons/sale_blanket_order_invoice_shipping_partner/models/__init__.py
odoo/addons/sale_blanket_order_invoice_shipping_partner/models/blanket_order.py
odoo/addons/sale_blanket_order_invoice_shipping_partner/static/description/icon.png
odoo/addons/sale_blanket_order_invoice_shipping_partner/static/description/index.html
odoo/addons/sale_blanket_order_invoice_shipping_partner/tests/TEST_INSTRUCTIONS.rst
odoo/addons/sale_blanket_order_invoice_shipping_partner/views/view_blanket_order_form.xml
odoo/addons/sale_blanket_order_invoice_shipping_partner/wizard/__init__.py
odoo/addons/sale_blanket_order_invoice_shipping_partner/wizard/create_sale_orders.py
odoo_addon_sale_blanket_order_invoice_shipping_partner-16.0.1.0.0.dist-info/METADATA
odoo_addon_sale_blanket_order_invoice_shipping_partner-16.0.1.0.0.dist-info/WHEEL
odoo_addon_sale_blanket_order_invoice_shipping_partner-16.0.1.0.0.dist-info/top_level.txt
odoo_addon_sale_blanket_order_invoice_shipping_partner-16.0.1.0.0.dist-info/RECORD
